Metadata-Version: 1.2
Name: reports
Version: 0.4.1
Summary: Quickly create HTML reports using a set of JINJA templates
Home-page: https://github.com/cokelaer/reports/
Author: Thomas Cokelaer
Author-email: cokelaer@gmail.com
Maintainer: Thomas Cokelaer
Maintainer-email: cokelaer@gmail.com
License: BSD3
Download-URL: https://pypi.python.org/pypi/reports
Keywords: HTML,table,jinja,report,reports
Platform: Linux
Platform: Unix
Platform: MacOsX
Platform: Windows
Classifier: Development Status :: 5 - Production/Stable
Classifier: Intended Audience :: Developers
Classifier: Intended Audience :: Science/Research
Classifier: License :: OSI Approved :: BSD License
Classifier: Operating System :: OS Independent
Classifier: Programming Language :: Python :: 3.7
Classifier: Programming Language :: Python :: 3.8
Classifier: Programming Language :: Python :: 3.9
Classifier: Topic :: Software Development :: Libraries :: Python Modules
Classifier: Topic :: Scientific/Engineering :: Bio-Informatics
Classifier: Topic :: Scientific/Engineering :: Information Analysis
Classifier: Topic :: Scientific/Engineering :: Mathematics
Classifier: Topic :: Scientific/Engineering :: Physics
